jadio_publisher/__init__.py
jadio_publisher/cli/__init__.py
jadio_publisher/cli/build.py
jadio_publisher/cli/bump.py
jadio_publisher/cli/clicommands.json
jadio_publisher/cli/git.py
jadio_publisher/cli/go.py
jadio_publisher/cli/help.py
jadio_publisher/cli/init.py
jadio_publisher/cli/main.py
jadio_publisher/cli/pypi.py
jadio_publisher/cli/show.py
jadio_publisher-0.0.1.dist-info/METADATA
jadio_publisher-0.0.1.dist-info/WHEEL
jadio_publisher-0.0.1.dist-info/entry_points.txt
jadio_publisher-0.0.1.dist-info/licenses/LICENSE
jadio_publisher-0.0.1.dist-info/RECORD
